feyndraw/__init__.py
feyndraw/basicdraw.py
feyndraw/geometry.py
feyndraw/loops.py
feyndraw/propagators.py
feyndraw/vertices.py
feyndraw-1.0.2.dist-info/METADATA
feyndraw-1.0.2.dist-info/WHEEL
feyndraw-1.0.2.dist-info/RECORD
