Metadata-Version: 2.4
Name: feyndraw
Version: 1.0.2
Summary: Drawing Feynman diagrams with matplotlib
Project-URL: Repository, https://github.com/schhug/feyndraw
Author-email: Hugo Schérer <hugo.scherer@mail.mcgill.ca>
License-Expression: MIT
Keywords: Feynman,diagram,draw,particle,physics
Classifier: Operating System :: OS Independent
Classifier: Programming Language :: Python :: 3
Requires-Python: >=3.0
Requires-Dist: matplotlib
Requires-Dist: numpy
